{
    "detailed payment": {
        "generator payments": {
            "g1": {
                "RTM energy payment": [
                    70.25399147477906,
                    -100.43835657817307,
                    57.57057761679934,
                    -30.33131676432101,
                    -73.38952381835445,
                    -222.25215390486179,
                    -50.797115848133,
                    -121.68098714069879,
                    -157.01156367155482,
                    -252.4773039707482,
                    -121.14814867962842,
                    -182.9751745433209,
                    -203.26933971199782,
                    -285.73247558114855,
                    -150.85895388238137,
                    -194.11755805804782,
                    -198.11467781785817,
                    -271.73376622586034,
                    -106.64008430367122,
                    -137.0106171381681,
                    -108.24216246986656,
                    -173.0122271851421,
                    70.22732164096197,
                    89.09840124467388,
                    169.5373773947252,
                    156.38910300943422,
                    469.47508795484816,
                    489.98041891792786,
                    -19.612723120444695,
                    -91.66131111058914,
                    169.4894337866139,
                    114.81796811822068,
                    108.2272128406864,
                    -5.758714190726563,
                    235.98088963856705,
                    173.37789580767603,
                    159.22033962075167,
                    33.437767601928954,
                    274.4938116058591,
                    204.04599245338366,
                    191.12083825367824,
                    46.646371040819645,
                    274.6133333786153,
                    201.88250598868342,
                    157.42443871251936,
                    9.995027135565149,
                    234.48390128115656,
                    154.10674456348755,
                    122.76368528944082,
                    -36.909448398685385,
                    197.47852901551238,
                    123.33121365744098,
                    89.04240107995113,
                    -43.14122868975789,
                    183.98270698494855,
                    122.20296466389193,
                    97.0632154309582,
                    -51.1788525651998,
                    193.4925034548969,
                    126.1078869761012,
                    92.15542696331629,
                    -65.14807401029944,
                    168.17402577589957,
                    114.91158561961504,
                    95.4186438841194,
                    -52.96354019247252,
                    185.40918889792468,
                    138.5627756471829,
                    132.14344944066735,
                    -0.5682423941106663,
                    262.7603177037058,
                    238.25053265252282,
                    213.0149459376086,
                    80.85016849623425,
                    375.0643477750284,
                    337.96482859658397,
                    304.67332495853566,
                    136.63504802698432,
                    367.2964491433644,
                    294.39772823992547,
                    219.07564998137443,
                    51.57455524727965,
                    259.02980286704894,
                    179.16734441107153,
                    104.55969190273501,
                    -71.10052517637241,
                    123.4113611119478,
                    11.215021326367086,
                    -54.081809177208726,
                    -229.6093729890454,
                    -77.36225588830628,
                    -195.1868059690134,
                    -283.71303415868204,
                    -308.84085682714027,
                    -357.09754520651717,
                    -326.47831871863366
                ],
                "energy payment": 469675.4810369963,
                "up-FRP payment": 24078.930789001584,
                "down-FRP payment": -0.0,
                "make-whole payment": 0.0,
                "total payment": 493754.4118259979
            },
            "g2": {
                "RTM energy payment": [
                    0.0,
                    0.0,
                    0.0,
                    0.0,
                    0.0,
                    0.0,
                    0.0,
                    0.0,
                    0.0,
                    0.0,
                    0.0,
                    0.0,
                    0.0,
                    0.0,
                    0.0,
                    0.0,
                    0.0,
                    0.0,
                    0.0,
                    0.0,
                    0.0,
                    0.0,
                    0.0,
                    0.0,
                    0.0,
                    0.0,
                    0.0,
                    0.0,
                    0.0,
                    0.0,
                    0.0,
                    0.0,
                    0.0,
                    0.0,
                    0.0,
                    0.0,
                    0.0,
                    0.0,
                    0.0,
                    0.0,
                    0.0,
                    0.0,
                    0.0,
                    0.0,
                    0.0,
                    0.0,
                    0.0,
                    0.0,
                    0.0,
                    0.0,
                    0.0,
                    0.0,
                    0.0,
                    0.0,
                    0.0,
                    0.0,
                    0.0,
                    0.0,
                    0.0,
                    0.0,
                    0.0,
                    0.0,
                    0.0,
                    0.0,
                    0.0,
                    0.0,
                    0.0,
                    0.0,
                    0.0,
                    0.0,
                    0.0,
                    0.0,
                    0.0,
                    0.0,
                    0.0,
                    0.0,
                    0.0,
                    0.0,
                    0.0,
                    0.0,
                    0.0,
                    0.0,
                    0.0,
                    0.0,
                    0.0,
                    0.0,
                    0.0,
                    0.0,
                    0.0,
                    0.0,
                    0.0,
                    0.0,
                    0.0,
                    0.0,
                    0.0,
                    0.0
                ],
                "energy payment": 0.0,
                "up-FRP payment": 0.0,
                "down-FRP payment": -0.0,
                "make-whole payment": 0.0,
                "total payment": 0.0
            },
            "g3": {
                "RTM energy payment": [
                    0.0,
                    0.0,
                    0.0,
                    0.0,
                    0.0,
                    0.0,
                    0.0,
                    0.0,
                    0.0,
                    0.0,
                    0.0,
                    0.0,
                    0.0,
                    0.0,
                    0.0,
                    0.0,
                    0.0,
                    0.0,
                    0.0,
                    0.0,
                    0.0,
                    0.0,
                    0.0,
                    0.0,
                    0.0,
                    0.0,
                    0.0,
                    0.0,
                    0.0,
                    0.0,
                    0.0,
                    0.0,
                    0.0,
                    0.0,
                    0.0,
                    0.0,
                    0.0,
                    0.0,
                    0.0,
                    0.0,
                    0.0,
                    0.0,
                    0.0,
                    0.0,
                    0.0,
                    0.0,
                    0.0,
                    0.0,
                    0.0,
                    0.0,
                    0.0,
                    0.0,
                    0.0,
                    0.0,
                    0.0,
                    0.0,
                    0.0,
                    0.0,
                    0.0,
                    0.0,
                    0.0,
                    0.0,
                    0.0,
                    0.0,
                    0.0,
                    0.0,
                    0.0,
                    0.0,
                    0.0,
                    0.0,
                    0.0,
                    0.0,
                    0.0,
                    0.0,
                    0.0,
                    0.0,
                    0.0,
                    0.0,
                    0.0,
                    0.0,
                    0.0,
                    0.0,
                    0.0,
                    0.0,
                    0.0,
                    0.0,
                    0.0,
                    0.0,
                    0.0,
                    0.0,
                    0.0,
                    0.0,
                    0.0,
                    0.0,
                    0.0,
                    0.0
                ],
                "energy payment": 0.0,
                "up-FRP payment": 0.0,
                "down-FRP payment": -0.0,
                "make-whole payment": 0.0,
                "total payment": 0.0
            },
            "g4": {
                "RTM energy payment": [
                    0.0,
                    0.0,
                    0.0,
                    0.0,
                    0.0,
                    0.0,
                    0.0,
                    0.0,
                    0.0,
                    0.0,
                    0.0,
                    0.0,
                    0.0,
                    0.0,
                    0.0,
                    0.0,
                    0.0,
                    0.0,
                    0.0,
                    0.0,
                    0.0,
                    0.0,
                    0.0,
                    0.0,
                    0.0,
                    0.0,
                    0.0,
                    0.0,
                    0.0,
                    0.0,
                    0.0,
                    0.0,
                    0.0,
                    0.0,
                    0.0,
                    0.0,
                    0.0,
                    0.0,
                    0.0,
                    0.0,
                    0.0,
                    0.0,
                    0.0,
                    0.0,
                    0.0,
                    0.0,
                    0.0,
                    0.0,
                    0.0,
                    0.0,
                    0.0,
                    0.0,
                    0.0,
                    0.0,
                    0.0,
                    0.0,
                    0.0,
                    0.0,
                    0.0,
                    0.0,
                    0.0,
                    0.0,
                    0.0,
                    0.0,
                    0.0,
                    0.0,
                    0.0,
                    0.0,
                    0.0,
                    0.0,
                    0.0,
                    0.0,
                    0.0,
                    0.0,
                    0.0,
                    0.0,
                    0.0,
                    0.0,
                    0.0,
                    0.0,
                    0.0,
                    0.0,
                    0.0,
                    0.0,
                    0.0,
                    0.0,
                    0.0,
                    0.0,
                    0.0,
                    0.0,
                    0.0,
                    0.0,
                    0.0,
                    0.0,
                    0.0,
                    0.0
                ],
                "energy payment": 0.0,
                "up-FRP payment": 0.0,
                "down-FRP payment": -0.0,
                "make-whole payment": 0.0,
                "total payment": 0.0
            },
            "g5": {
                "RTM energy payment": [
                    0.0,
                    0.0,
                    0.0,
                    0.0,
                    0.0,
                    0.0,
                    0.0,
                    0.0,
                    0.0,
                    0.0,
                    0.0,
                    0.0,
                    0.0,
                    0.0,
                    0.0,
                    0.0,
                    0.0,
                    0.0,
                    0.0,
                    0.0,
                    0.0,
                    0.0,
                    0.0,
                    0.0,
                    0.0,
                    0.0,
                    0.0,
                    0.0,
                    567.8275166604201,
                    567.8275166604201,
                    567.8275166604201,
                    567.8275166604201,
                    567.8275166604201,
                    567.8275166604201,
                    567.8275166604201,
                    567.8275166604201,
                    567.8275166604201,
                    567.8275166604201,
                    567.8275166604201,
                    567.8275166604201,
                    567.8275166604201,
                    567.8275166604201,
                    567.8275166604201,
                    567.8275166604201,
                    567.8275166604201,
                    567.8275166604201,
                    567.8275166604201,
                    567.8275166604201,
                    567.8275166604201,
                    567.8275166604201,
                    567.8275166604201,
                    567.8275166604201,
                    567.8275166604201,
                    567.8275166604201,
                    567.8275166604201,
                    567.8275166604201,
                    567.8275166604201,
                    567.8275166604201,
                    567.8275166604201,
                    567.8275166604201,
                    567.8275166604201,
                    567.8275166604201,
                    567.8275166604201,
                    567.8275166604201,
                    567.8275166604201,
                    567.8275166604201,
                    567.8275166604201,
                    567.8275166604201,
                    567.8275166604201,
                    567.8275166604201,
                    567.8275166604201,
                    567.8275166604201,
                    567.8275166604201,
                    567.8275166604201,
                    567.8275166604201,
                    567.8275166604201,
                    567.8275166604201,
                    567.8275166604201,
                    567.8275166604201,
                    567.8275166604201,
                    567.8275166604201,
                    567.8275166604201,
                    567.8275166604201,
                    567.8275166604201,
                    567.8275166604201,
                    567.8275166604201,
                    567.8275166604201,
                    567.8275166604201,
                    567.8275166604201,
                    499.793421169915,
                    567.8275166604201,
                    567.8275166604201,
                    499.793421169915,
                    499.793421169915,
                    499.793421169915,
                    499.793421169915
                ],
                "energy payment": 108253.15664090254,
                "up-FRP payment": 27962.36719109969,
                "down-FRP payment": 0.0,
                "make-whole payment": 0.0,
                "total payment": 136215.52383200222
            }
        }
    },
    "total energy payments": 577928.6376778989,
    "total up-FRP payments": 52041.29798010127,
    "total down-FRP payments": 0.0,
    "total make-whole payments": 0.0,
    "total payment": 629969.9356580001
}
